groundx/__init__.py
groundx/api_client.py
groundx/api_response.py
groundx/apis/__init__.py
groundx/apis/path_to_api.py
groundx/apis/paths/__init__.py
groundx/apis/paths/v1_bucket.py
groundx/apis/paths/v1_bucket_bucket_id.py
groundx/apis/paths/v1_customer.py
groundx/apis/paths/v1_group.py
groundx/apis/paths/v1_group_group_id.py
groundx/apis/paths/v1_group_group_id_bucket_bucket_id.py
groundx/apis/paths/v1_health.py
groundx/apis/paths/v1_health_service.py
groundx/apis/paths/v1_ingest_document_document_id.py
groundx/apis/paths/v1_ingest_documents.py
groundx/apis/paths/v1_ingest_documents_id.py
groundx/apis/paths/v1_ingest_documents_local.py
groundx/apis/paths/v1_ingest_documents_remote.py
groundx/apis/paths/v1_ingest_documents_website.py
groundx/apis/paths/v1_ingest_process_id.py
groundx/apis/paths/v1_search_documents.py
groundx/apis/paths/v1_search_id.py
groundx/apis/tag_to_api.py
groundx/apis/tags/__init__.py
groundx/apis/tags/buckets_api.py
groundx/apis/tags/buckets_api_generated.py
groundx/apis/tags/customer_api.py
groundx/apis/tags/customer_api_generated.py
groundx/apis/tags/documents_api.py
groundx/apis/tags/documents_api_generated.py
groundx/apis/tags/groups_api.py
groundx/apis/tags/groups_api_generated.py
groundx/apis/tags/health_api.py
groundx/apis/tags/health_api_generated.py
groundx/apis/tags/search_api.py
groundx/apis/tags/search_api_generated.py
groundx/client.py
groundx/client.pyi
groundx/client_custom.py
groundx/configuration.py
groundx/exceptions.py
groundx/exceptions_base.py
groundx/model/__init__.py
groundx/model/bounding_box_detail.py
groundx/model/bounding_box_detail.pyi
groundx/model/bucket_create_request.py
groundx/model/bucket_create_request.pyi
groundx/model/bucket_detail.py
groundx/model/bucket_detail.pyi
groundx/model/bucket_list_response.py
groundx/model/bucket_list_response.pyi
groundx/model/bucket_response.py
groundx/model/bucket_response.pyi
groundx/model/bucket_update_detail.py
groundx/model/bucket_update_detail.pyi
groundx_python_sdk-1.3.30.dist-info/LICENSE
groundx_python_sdk-1.3.30.dist-info/METADATA
groundx_python_sdk-1.3.30.dist-info/WHEEL
groundx_python_sdk-1.3.30.dist-info/RECORD
