Metadata-Version: 2.3
Name: groundx-python-sdk
Version: 1.3.30
Summary: Client for GroundX APIs
License: MIT
Author: Konfig
Author-email: support@eyelevel.ai
Requires-Python: >=3.7,<4.0
Classifier: License :: OSI Approved :: MIT License
Classifier: Programming Language :: Python :: 3
Classifier: Programming Language :: Python :: 3.7
Classifier: Programming Language :: Python :: 3.8
Classifier: Programming Language :: Python :: 3.9
Classifier: Programming Language :: Python :: 3.10
Classifier: Programming Language :: Python :: 3.11
Classifier: Programming Language :: Python :: 3.12
Classifier: Programming Language :: Python :: 3.13
Requires-Dist: aiohttp (>=3.8.4,<4.0.0)
Requires-Dist: certifi (>=2023.7.22)
Requires-Dist: cryptography (>=42.0.5,<43.0.0)
Requires-Dist: frozendict (>=2.3.4,<3.0.0)
Requires-Dist: python-dateutil (>=2.8.2,<3.0.0)
Requires-Dist: typing_extensions (>=4.3.0,<5.0.0)
Requires-Dist: urllib3 (>=1.26.18,<3.0.0)
